prosto/Column.py
prosto/ColumnOperation.py
prosto/Data.py
prosto/Operation.py
prosto/Prosto.py
prosto/Table.py
prosto/TableOperation.py
prosto/Topology.py
prosto/__init__.py
prosto/column_sql.py
prosto/column_sql.txt
prosto/main.py
prosto/resolve.py
prosto/utils.py
prosto-0.6.0.dist-info/LICENSE
prosto-0.6.0.dist-info/METADATA
prosto-0.6.0.dist-info/WHEEL
prosto-0.6.0.dist-info/top_level.txt
prosto-0.6.0.dist-info/zip-safe
prosto-0.6.0.dist-info/RECORD
