Metadata-Version: 2.1
Name: prosto
Version: 0.6.0
Summary: Data processing toolkit radically changing the way data is processed
Home-page: https://github.com/asavinov/prosto
Author: Alexandr Savinov
Author-email: savinov@conceptoriented.org
License: MIT License
Keywords: data processing,analytics,data science,pandas,map-reduce,feature engineering,business intelligence
Platform: UNKNOWN
Classifier: Development Status :: 4 - Beta
Classifier: Programming Language :: Python
Classifier: Programming Language :: Python :: 3.6
Classifier: License :: OSI Approved :: MIT License
Classifier: Operating System :: OS Independent
Classifier: Intended Audience :: Developers 
Classifier: Intended Audience :: Science/Research
Classifier: Topic :: Scientific/Engineering
Classifier: Topic :: Software Development
License-File: LICENSE
Requires-Dist: numpy
Requires-Dist: pandas
